{
  "CartoonQty": "CartoonQtyCh",

  "LoginHeading": "登入你的 FRAYTE 帳戶",
  "LoginUsername": "用戶名稱",
  "LoginUsernamePlaceholder": "用戶名稱",
  "LoginUsernameValidError": "請提供用戶名稱",
  "LoginPassword": "密碼",
  "LoginPasswordValidError": "請提供密碼",
  "LoginForgotPass": "忘記密碼？",
  "LoginRecoverNow": "立即重設密碼",
  "New": "新",
  "Current": "現時密碼",
  "Frayte": "FRAYTE",
  "System": "系統",
  "Login": "登入",
  "Logout": "登出",
  "MyProfile": "我的個人檔案",
  "LogisticLTD": "物流 LTD",
  "AllRightsReserved": "版權所有 不得轉載",
  "Welcome": "歡迎",
  "Send": "傳送",
  "ForgotPassword": "忘記密碼？",
  "ForgotPasswordSubText": "不用擔心，請提供你的電郵地址，我們會為你重設密碼。",
  "Enter": "輸入",
  "EnterEmailAdd": "輸入你的電郵地址",

  "Detail": "詳細資料",
  "BasicDetail": "基本資料",
  "FrayteAssociatedUser": "FRAYTE 關聯用戶",
  "AssociatedUser": "關聯用戶",
  "OtherAddress": "其他地址",
  "ChooseOther": "選擇其它",
  "AddAddress": "新增地址",
  "Tradelane": "貨運路線",
  "TradeLanes": "貨運路線",
  "AddTradelane": "新增貨運路線",
  "PickupAddressBook": "選擇地址簿",
  "Book": "簿",
  "AssociateUser": "關聯用戶",
  "AddAssociateUser": "新增關聯用戶",
  "AddWarehouse": "新增倉庫",

  "ShipmentMethod": "運送方法",
  "Air": "空運",
  "Sea": "海運",
  "Courier": "速遞",
  "COURIER": "速遞",
  "Freight": "貨物運輸",
  "MainAddress": "主要地址",
  "Owner": "擁有者",
  "Company": "公司",
  "Yes": "是",
  "Save": "儲存",
  "Cancel": "取消",
  "Next": "下一步",
  "Previous": "上一步",
  "PlaceBooking": "確定訂單",
  "Shipper": "寄件人",
  "Receiver": "收件人",

  "Account": "帳戶",
  "Validation": "驗證",
  "Delete": "刪除",
  "Remove": "移除",
  "Edit": "編輯",
  "Modify": "修改",
  "Change": "更改",
  "Confirm": "確定",
  "Profile": "個人檔案",
  "Description": "描述",
  "Holiday": "假期",
  "HolidayDate": "假期日期",
  "HolidayValidError": "需要提供假期日期",
  "Associated": "關聯",
  "Submit": "提交",
  "List": "清單",
  "Flight": "航班",
  "ExpressCargo": "貨物速遞",
  "ShipmentVia": "運輸途徑",
  "ShipmentViaValidError": "需要提供運輸途徑",

  "Country": "國家/地區",
  "CountrySelectedOption": "選擇國家/地區（必需）",
  "CountryValidationError": "必需提供國家/地區",

  "Name": "姓名",
  "NamePlaceholder": "姓名（必需）",
  "NameValidationError": "必需提供姓名",

  "NickName": "別名",
  "NickNamePlaceholder": "別名（必需）",
  "NickNameValidationError": "必需提供別名",

  "Contact": "聯絡人名稱",
  "ContactPlaceholder": "聯絡人名稱（必需）",
  "ContactValidationError": "必需提供聯絡人名稱",

  "CompanyName": "公司名稱",
  "CompanyNamePlaceholder": "公司名稱（必需）",
  "CompanyNameValidationError": "必需提供公司名稱",

  "Address": "地址",
  "AddressPlaceholder": "地址 1（必需）",
  "AddressValidationError": "必需提供地址",

  "Address1": "地址1",
  "Address2": "地址2",
  "Address3": "地址3",
  "Suburb": "郊區",

  "Date": "日期",
  "DatePlaceholder": "dd/MM/yyyy（必需）",
  "DateValidError": "必需提供日期",
  "OtherPickupAddress": "其他取貨地址",

  "PostalCode": "郵政編碼",
  "PostalCodePlaceholder": "郵政編碼（必需）",
  "PostalCodeValidationError": "必需提供郵政編碼",

  "City": "城市",
  "CityPlaceholder": "城市（必需）",
  "CityValidationError": "必需提供城市",

  "State": "州/省",
  "StatePlaceholder": "州/省（必需）",
  "StateValidationError": "必需提供州/省",

  "CountryCodePlaceholder": "選擇國家/地區代碼",
  "CountryCodeValidationError": " 必需提供國家/地區代碼",

  "CompanyTelephone": "公司電話",
  "CompanyTelephoneErrorMessage": "必需提供公司電話",
  "No": "無",
  "Telephone": "電話",
  "TelephonePlaceholder": "電話號碼（必需）",
  "TelephoneValidationError": "必需提供電話號碼",

  "Mobile": "手機",
  "MobilePlaceholder": "手機號碼",
  "CompanyMobile": "公司手機號碼",

  "Fax": "傳真",
  "FaxPlaceholder": "傳真號碼",
  "CompanyFax": "公司傳真號碼",

  "Email": "電郵",
  "EmailPlaceholder": "電郵地址（必需）",
  "EmailValidationError": "必需提供電郵地址",
  "EmailNotValid": "電郵地址不正確",
  "EmailAlreadyExist": "電郵地址已被使用",

  "Tax": "稅",
  "TaxPlaceholder": "稅務代碼/增值稅號碼",
  "TaxValidationError": "必需提供稅務代碼/增值稅號碼",

  "TimeZone": "時區",
  "TimeZoneValidationError": "必需提供時區",
  "TimeZoneSelectedOption": "選擇時區（必需）",

  "ETD": "（預計出發時間）",
  "ETDValidError": "必需提供（預計出發時間）",
  "ETA": "（預計到達的時間）",
  "ETAValidError": "必需提供（預計到達的時間）",
  "Time": "時間",
  "TimeNotValid": "時間不正確",
  "TimePlaceholder": "hh:mm",
  "TimeValidationError": "必需提供時間",

  "WorkingStartTime": "工作開始時間",
  "WorkingEndTime": "工作結束時間",

  "OfficeStartTime": "辦公室開始服務時間",
  "OfficeEndTime": "辦公室結束服務時間",
  "Hours24": "（24 小時）",

  "Warehouse": "倉庫",
  "WarehousePlaceholder": "選擇倉庫（必需）",



  "ProcessBox_AddressDetails": "地址詳細資料",
  "ProcessBox_ShipmentDetails": "物流詳細資料",
  "ProcessBox_ServiceOptions": "服務選項",
  "ProcessBox_ConfirmShipment": "確認貨運",


  "address_PurchaseOrderNo": "採購訂單號碼",
  "address_PurchaseOrderNoTooltip": "請以 PO-XXXXXXXX 的格式輸入訂單號碼",
  "address_PurchaseOrderNoPlaceholder": "輸入採購訂單號碼",
  "address_PurchaseOrderNoValidError": "必需提供採購訂單號碼",
  "address_FrayteCustomerAccountNumber": "FRAYTE 客戶帳戶號碼",
  "address_FrayteCustomerAccountValidError": "必需提供FRAYTE 客戶帳戶號碼",
  "address_FrayteCustomerAccountInValidError": "帳戶號碼不正確",
  "address_ShipperDetails": "寄件人詳細資料",
  "address_ReceiverDetails": "收件人詳細資料",
  "ReceiverValidError": "必需提供收件人資料",

  "Shipment": "貨運",
  "shipment_ShipmentTerm": "貨運期限",
  "shipment_ShipmentTermSelectedOption": "選擇貨運期限（必需）",
  "shipment_ShipmentTermValidationError": "必需提供貨運期限",

  "shipment_PackagingType": "包裝方式",
  "shipment_PackagingTypeSelectedOption": "選擇包裝方式期限（必需）",
  "shipment_PackagingTypeValidationError": "必需提供包裝方式",

  "shipment_SpecialDeliveryNeeded": "特別送貨需要",
  "shipment_SpecialDeliveryNeededSelectedOption": "特別送貨",
  "shipment_SpecialDeliveryNeededValidationError": "必需提供包裝方式",

  "shipment_PieceDetailsHeading": "貨件詳細資料",
  "shipment_PieceDetailsUploadBtn": "上載 Excel 檔案",
  "shipment_PieceDetailsJobNumber": "項目編號",
  "shipment_PieceDetailsStyleNumber": "樣式編號",
  "shipment_PieceDetailsHSCode": "HS 代碼",
  "shipment_PieceDetailsCartonQty": "裝箱數量",
  "shipment_PieceDetailsPieces": "件數",
  "shipment_PieceDetailsWeightsKg": "重量（千克）",
  "shipment_PieceDetailsLcms": "長度（厘米）",
  "shipment_PieceDetailsWcms": "闊度（厘米）",
  "shipment_PieceDetailsHcms": "高度（厘米）",
  "shipment_PieceDetailsProductDesc": "貨品描述",
  "shipment_PieceDetailsProductDescPlaceHolder": "貨件内容",
  "shipment_TotalNoPieces": "總件數",
  "shipment_TotalEstimatedGrossWeight": "估計總重量",
  "TotalWeight": "總重量",
  "TotalDimWeight": "總體積重量",
  "shipment_TotalEstimatedChargeableWeight": "估計總收費重量",
  "shipment_Kgs": "千克",

  "PiecesDetailRemoveConfirmation": "貨品細節刪除確認",
  "PiecesDetailRemoveConfirmationText": "確定要刪除貨品細節？",

  "shipment_ShipmentDetailsHeading": "物流詳細資料",
  "shipment_ShipmentDetailsDescription": "貨品内容描述",
  "shipment_ShipmentDetailsDescriptionValidError": "必需提供貨品内容描述",
  "shipment_ShipmentDetailsShipmentType": "貨品類型",
  "shipment_ShipmentDetailsDocument": "文件",
  "shipment_ShipmentDetailsNonDocument": "非文件",
  "DuitableOrNot": "需否徵稅",
  "shipment_ShipmentDetailsShippingReference": "貨運參考編號",
  "shipment_ShipmentDetailsShippingReferenceValidError": "必需提供貨運參考編號",
  "shipment_ShipmentDetailsShippingDate": "送貨日期/時間",
  "shipment_ShipmentDetailsShippingDatePlaceholder": "dd/MM/yyyy 格式（必需）",
  "shipment_ShipmentDetailsShippingDateValidError": "必需提供送貨日期",
  "shipment_ShipmentDetailsShippingDateInValid": "送貨日期無效",
  "shipment_ShipmentDetailsShippingDateTimeValidError": "必需提供送貨時間",

  "shipment_ShipmentDetailsPaymentParty": "付款方",
  "shipment_ShipmentDetailsPaymentPartySubHead": "負責支付運費的一方",

  "shipment_CustomsInformation": "報關資料",
  "shipment_DeclaredValue": "申報價值",
  "shipment_Currency": "貨幣",
  "shipment_CurrencyPlaceHolder": "選擇貨幣",

  "ShipmentUpdateSuccess": "成功更新貨運訂單",
  "NewShipmentCreateSuccess": "成功建立新貨運訂單",
  "CongratulationSuccessfullyUpdatedShipment": "恭喜！已成功更新貨運訂單資料",
  "CustomerAndShipperGetUpdated": "客戶和寄件人會透過已登記的電郵地址收到更新的資料",
  "PleaseDownloadShipmentDetailPDF": "請從下載有貨運訂單詳細資料的 PDF",
  "Here": "在此下載",
  "ShipmentCongratsText1": "恭喜！已成功透過Fryate 管理系統建立新貨運訂單",
  "ShipmentCongratsText2": "客戶將會透過收到關於新貨運訂單的提示電郵",
  "ShipmentCongratsText3": "另外，我們已爲你建立登入憑證，確認電郵已經傳送至你已提供的電郵帳戶",
  "ShipmentCongratsText4": "下一次使用我們的服務，你可使用憑證登入系統建立新訂單，更快捷方便",


  "ShippingMethod": "送貨方式",
  "serviceoptn_ShippingMethod": "送貨方式",
  "serviceoptn_ShippingMethodSelectedOption": "選擇送貨方式（必需）",
  "serviceoptn_ShippingMethodValidError": "必需提供送貨方式",

  "serviceoptn_SchedulePickup": "安排取貨",

  "serviceoptn_LocationType": "地點類別",
  "serviceoptn_LocationTypeSelectedOption": "選擇地點類別（必需）",
  "serviceoptn_LocationTypeValidError": "必需提供地點類別",

  "serviceoptn_ContactPhoneNumber": "聯絡電話號碼",
  "serviceoptn_ContactPhoneNumberPlaceHolder": "聯絡電話號碼（必需）",
  "serviceoptn_ContactPhoneNumberValidError": "必需提供聯絡電話號碼",

  "serviceoptn_SpecialInstracutions": "特別指示",
  "serviceoptn_SpecialInstracutionsPlaceHolder": "特別指示（必需）",
  "serviceoptn_SpecialInstracutionsValidError": "必需提供特別指示",

  "serviceoptn_PickupDate": "取貨日期/時間",
  "serviceoptn_PickupDateValidError": "必需提供取貨日期",
  "serviceoptn_PickupDateInvalid": "取貨日期無效",

  "serviceoptn_TransportWarehouse": "貨件到倉庫的運輸方式",
  "serviceoptn_TransportWarehousePlaceholder": "請選擇貨件到倉庫的運輸方式",
  "serviceoptn_TransportWarehouseValidError": "必需提供貨件到倉庫的運輸方式",
  "ShipmentViaFrayteWarehouse": "透過 FRAYTE 倉庫出貨",

  "ShipmentReadyBy": "送件完成處理時間",
  "ShipmentCancelConfirm": "送件取消確認",
  "ShipmentCancelConfirmText": "確定要取消送件？",

  "TrackingNumber": "追踪號碼",
  "VehicleRegistrationNumber": "車輛登記號碼",


  "Ship_From": "寄件地址:",
  "Ship_To": "收件地址:",
  "T": "T",
  "E": "E",
  "confirmShp_ShipmentDetail": "貨件詳細資料",
  "confirmShp_ShipmentDate": "送貨日期",
  "confirmShp_PackingType": "包裝類型",
  "confirmShp_NumberOfPieces": "件數",
  "confirmShp_TotalWeight": "總重量",
  "confirmShp_ShipperReference": "寄件人參考資料 ",
  "confirmShp_DescriptionOfContent": "貨件內容描述",

  "confirmShp_terms1": "我已閱讀並接受",
  "confirmShp_terms2": "條款及細則",


  "AddCustomer": "新增客戶",

  "AccountNumber": "帳戶號碼",
  "OwnerName": "擁有人名稱",
  "OwnerNamePlaceHolder": "擁有人名稱（必需）",
  "OwnerNameValidError": "必需提供擁有人名稱",
  "VATNo": "增值稅/商品及服務稅號碼",
  "VATNoPlaceHolder": "增值稅/商品及服務稅號碼",
  "BillingCurrency": "結算貨幣",
  "BillingCurrencySelectedOption": "選擇結算貨幣",
  "BillingCurrencyValidError": "必需提供結算貨幣",
  "CreditLimit": "信用限額",
  "CreditLimitPlaceHolder": "信用限額（必需）",
  "CreditLimitValidError": "必需提供信用限額",

  "TermsOfPaymentSelectedOption": "支付條款（必需）",
  "TermsOfPaymentValidError": "必需提供支付條款",

  "Type": "類型",

  "WorkingHrs": "工作時間",

  "LineManager": "直線經理",
  "LineManagerPlaceHolder": "請在此輸入直線經理名稱",

  "AccountDepartmentPlaceHolder": "請在此輸入會計名稱",
  "Documents": "文件",
  "DocumentsPlaceHolder": "請在此輸入文件名稱",
  "OperationStaff": "負責職員",
  "OperationStaffPlaceHolder": "請在此輸入負責職員名稱",
  "OperationStaffValidError": "必需提供負責職員名稱",
  "SalesRepresentative": "銷售代表",
  "SalesRepresentativePlaceHolder": "請在此輸入銷售代表名稱",


  "AddShipper": "新增寄件人",
  "LinkToShipper": "連接到寄件人",
  "SearchShipperAssignment": "搜尋寄件人進行指派操作",
  "Assigned": "已指派",


  "AddAgent": "新增代理",
  "Agent": "代理",
  "AgentValidError": "必需提供代理",


  "Manager": "經理",
  "Location": "地點",
  "SearchYourLocation": "搜尋你的位置",
  "SetMapLocation": "設定地圖位置",
  "ResetMapLocation": "重設地圖位置",


  "Carrier": "營運商",
  "AddCarrier": "新增營運商",
  "carrier_SelectType": "--選擇類型--",
  "CarrierTypeValidError": "必須提供營運商類型",
  "CarrierPlaceHolder": "營運商（必需）",
  "CarrierValidError": "必須提供營運商",
  "Code": "代碼",
  "CodeValidError": "必須提供代碼",
  "Prefix": "前綴",


  "User": "用戶",
  "AddUser": "新增用戶",
  "Skype": "Skype",
  "SkypePlaceHolder": "Skype（必需）",
  "SkypeValidError": "必須提供 Skype",

  "Position": "職位",
  "PositionPlaceHolder": "職位（必需）",
  "PositionValidError": "必須提供職位",

  "Role": "職位",
  "RoleSelectedOption": "選擇職位（必需）",
  "RoleValidError": "必須提供職位",


  "Offset": "抵消",
  "OffsetPlaceHolder": "抵消",
  "OffsetValidError": "必須為抵消狀態",
  "Select": "選擇",


  "Add": "新增",
  "Document": "文件",
  "TypePlaceHolder": "類型（必需）",
  "TypeValidError": "必須提供類型",
  "PublicHoliday": "公眾假期",


  "Shipping": "貨運",
  "Website": "網站",
  "LatestBookingTime": "最近的預訂時間",


  "Weekdays": "平日",
  "WeekdaysValidError": "必須為平日",
  "Days": "日數",
  "One": "一",
  "Two": "二",
  "Three": "三",
  "Four": "四",
  "Five": "五",
  "1": "1",
  "2": "2",
  "3": "3",
  "4": "4",
  "5": "5",
  "6": "6",
  "7": "7",

  "Order": "訂單",
  "Hash": "#",
  "HashValidError": "必須為 #",
  "Delivery": "送貨",
  "Invalid": "無效",
  "Download": "下載",

  "OK": "確定",
  "Upload": "上載",
  "In": "in",
  "AWB": "空運訂單",
  "AWBValidError": "必須為空運訂單",
  "Attach": "附加",
  "Commercial": "商業",
  "Invoice": "發票",
  "InvoiceValidError": "需要提供發票",
  "Update": "更新",
  "DropOff": "放下",
  "DateAndTime": "日期及時間",
  "DateAndTimeValidError": "需要提供日期及時間",
  "Destination": "目的地",
  "OtherDocs": "其他文件",
  "POD": "交貨證明",
  "AirWayBill": "航空貨運單",
  "AirWayBillValidError": "需要為航空貨運單",
  "Signature": "簽名",
  "SignatureValidError": "需要提供簽名",
  "PleaseUploadAWBDocuments": "請上載你的航空貨運單檔案",
  "Image": "圖像",
  "Confirmed": "已確認",
  "Rejected": "已拒絕",
  "ConfirmedNewShipmentBooking": "已確認新貨運訂單",
  "RejectNewShipment": "拒絕新貨運訂單",
  "RejectionReason": "拒絕原因",
  "RejectionReasonValidError": "需要提供拒絕原因",
  "Anticipated": "預計",
  "UpdateAnticipatedDateTime": "更新預計日期和時間",
  "By": "此時間前",
  "Originating": "起點",
  "OriginatingCountrySelectedOption": "選擇起點國家/地區（必需）",
  "OriginatingAgentSelectedOption": "選擇起點代理（必需）",
  "DestinationCountrySelectedOption": "選擇目的地國家/地區（必需）",
  "DestinationAgentSelectedOption": "選擇目的地代理（必需）",
  "Direct": "直接送貨",
  "Deferred": "延期",
  "DirectDeferredValidError": "需要提供直接送貨/延期資料",

  "RequestedTransitTime": "要求的送貨時間",
  "PleaseSelect": "請選擇",

  "PackingList": "裝箱清單",
  "Customs": "海關",
  "PleaseUploadShipmentDocuments": "請上載你的貨運單據",

  "AgentUploadMasterAWBDocument": "代理上載主要空運訂單文件",

  "CustomerAndOtherIssue": "如遇到海關或其他問題，令送貨受阻，請說明",
  "ChooseNewAgent": "選擇新代理",

  "FrayteShipmentValidText": "部分資料不完整或沒有正確完成所有設定新貨運訂單的步驟",
  "FrayteShipmentValidReCheckText": "請重新檢查第 1 步的貨運訂單資料（地址資料部分）",

  "ClickHereToGoTo": "點按這裡到",
  "AddressInformation": "地址資料",
  "CheckShipmentInformation": "或按下「上一步」按鍵檢查資料是否正確",

  "TermAndConditionDetail": "條款及細則詳細資料",

  "CustomerConfirmShipThankyou": "感謝確認貨運訂單。你的訂單正在處理中",
  "CustomerConfirmShipThankyouTxt": "你將收到有關貨運的電郵，你也可以登入到 FRAYTE 查看貨件的目前狀態",
  "CustomerConfirmThankResponse": "謝謝你的回應",
  "CustomerRejectNewShipment": "新的貨運訂單被拒絕",


  "More": "更多",
  "Working": "有效",
  "This": "此項目",
  "The": "the",
  "DeleteHeader": "確認刪除",
  "DeleteBody": "確定要刪除嗎",

  "FrayteError": "FRAYTE-錯誤",
  "FrayteInformation": "FRAYTE-資訊",
  "FrayteValidation": "FRAYTE-驗證",
  "FrayteSuccess": "FRAYTE-成功",
  "FrayteWarning": "FRAYTE-提示",

  "ErrorSavingRecord": "儲存記錄時發生錯誤",
  "ErrorDeletingRecord": "刪除記錄時發生錯誤",

  "PleaseCorrectValidationErrors": "請先修正驗證錯誤。",
  "SuccessfullySavedInformation": "成功儲存資訊",
  "SuccessfullyDelete": "刪除成功",

  "ErrorGetting": "獲取資料時發生錯誤",
  "setting": "設定",
  "detail": "詳細資料",
  "DEtail": "详情",
  "receiver": "收件人",
  "information": "資料",
  "records": "記錄",
  "Branch": "分行",
  "current": "現時",
  "past": "過去",
  "shipments": "貨運",
  "agent": "代理",
  "user": "用戶",
  "staff": "職員",
  "courier": "速遞",
  "country": "國家/地區",
  "document": "文件",
  "timezone": "時區",
  "access": "存取",

  "ErrorWhileCommunicatingServer": "嘗試與伺服器連線時發生錯誤，請稍候再試。",
  "EmailAddressNotFound": "找不到電郵地址，請使用正確的電郵地址再試一次",
  "SuccessfullySentMailTo": "成功發送電郵至",
  "PleaseCheckYourMail": "請檢查電郵。",

  "PleaseEnterValidUserPass": "請輸入正確的用戶名稱/密碼",
  "ErrorWhileLogin": "登入時發生錯誤",

  "SuccessfullyChangedPassword": "成功更改密碼。",
  "ErrorOccuredDuringUpload": "上載發生錯誤",
  "UploadedSuccessfully": "成功上載",
  "InternalServerErrorOccurred": "發生內部伺服器錯誤。",

  "PleaseAttachDocument": "請附加檔案",
  "PleaseSelectValidFile": "請選擇有效的檔案。支援的檔案類型包括：圖片、PDF、Word 檔案、Excel 和文字檔案",

  "ThankyouConformedSuccessfully": "謝謝 –上載成功",
  "CouldNotConfirmAgent": "無法確認代理。",
  "ThankyouForYourValuableFeedback": "感謝您的寶貴意見",
  "SomeErrorOccured": "發生錯誤",
  "PleaseTryLater": "請稍後再試。",

  "AnticipatedDateTimeUpdatedSuccessfully": "成功更新預計日期和時間",
  "CouldNotUpdateAnticipatedDateTime": "無法更新預計日期和時間。",

  "FlightDetailConformedSuccessfully": "成功確認航班資料",
  "CouldNotUpdateFlightDetail": "無法更新航班資料",

  "AgentSelectedSuccessfully": "成功選擇代理",
  "CouldNotSelectAgent": "無法選擇代理。",

  "CouldNotFindShipmentConfirmationDetail": "無法找到貨運詳細資料。請透過電郵上的確認連結查詢。",

  "CouldNotUpdateInformation": "無法更新資料",
  "DropOffInformationUpdatedSuccessfully": "成功更新派送資料",

  "AWBConfirmation": "AWB 確認",
  "MailSentToConsigneeGoodsPickup": "已經發送電郵到成功取貨的收件人",

  "AddressSelection": "地址選擇",
  "PleaseSelectAddress": "請選擇地址",

  "PleaseSelectionDeliveryOption": "請選擇送貨選項",
  "ErrorSavingShipment": "儲存貨運資料時發生錯誤",
  "PleaseSelectTermAndConditions": "請先選擇條款及細則。",
  "ErrorGettingShipmentDetailServer": "從伺服器獲取貨運資料時發生錯誤",

  "Number": "數量",
  "NumberValidError": "必須提供數量",
  "AccountNumberValidError": "必須提供帳戶號碼",
  "DocumentValidError": "必須提供檔案",

  "WeekDay": "平日",
  "WeekDays": "平日",
  "Monday": "星期一",
  "Tuesday": "星期二",
  "Wednesday": "星期三",
  "Thursday": "星期四",
  "Friday": "星期五",
  "Saturday": "星期六",
  "Sunday": "星期日",
  "Half": "半日",

  "Sample": "例子",
  "Excel": "Excel",
  "TermsAndCondition": "條款及細則",
  "WeekdaysSelectedOption": "選擇平日（必須）",

  "DescriptionValidationError": "必須提供描述",
  "DeliveryValidError": "必須提供送貨資料",

  "Telex": "電傳",
  "Bill": "賬單",
  "Port": "港口",
  "Lading": "貨運提單",
  "LadingValidError": "貨運提單貨運提單",
  "Vsl": "VSL",
  "Of": "於",
  "Stamp": "蓋印/簽名",
  "StampValidError": "必須提供蓋印/簽名",

  "Planned": "已計劃",
  "Departure": "離境",
  "Arrival": "入境",
  "PTD": "計劃出發時間",
  "PTA": "計劃到達時間",
  "PutDetailInformation": "請輸入以下詳細資料",

  "Chinese": "中文",
  "QuickBooking": "快速預訂",
  "Setting": "設定",
  "Settings": "設定",
  "ManageDetail": "管理詳細資料",
  "NewShipment": "新貨運",
  "CurrentShipment": "現時的貨運",
  "PastShipment": "過去的貨運",
  "PastShipments": "過去的貨運",
  "UseDifferentAddress": "使用其他地址",

  "Airway": "空運",
  "Sailing": "海運",
  "Vessel": "航運",

  "Zip": "郵政編碼",
  "OrigCountry": "原國家/地區",
  "OrigAgent": "原代理",
  "DestCountry": "目的地郵政編碼",
  "DestAgent": "目的地代理",

  "MobileNo": "手機號碼",
  "SO": "S.O#",
  "ShippedFrom": "寄件地",
  "ShippedTo": "收件地",
  "ShippingType": "貨運類型",
  "ShippingDate": "出貨日期",
  "Status": "狀態",
  "DateOfDelivery": "送貨日期",

  "UserType": "用戶類型",
  "WorkingTime": "工作時間",
  "WorkingDays": "工作日數",
  "LocationName": "位置名稱",
  "ManagerName": "姓名",
  "Phone": "電話",
  "ManagerEmail": "經理電郵",
  "CourierName": "速遞名稱",
  "CourierType": "速遞類別",
  "CountryName": "國家/地區名稱",
  "TimeZoneName": "時區名稱",
  "OffsetDetail": "抵消詳情",
  "Mon": "週一",
  "Tue": "週二",
  "Wed": "週三",
  "Thur": "週四",
  "Fri": "週五",
  "Sat": "週六",
  "Sun": "週日",
  "HalfDayTime": "半日及時間",



  "Our": "我們的",
  "Client": "客戶",
  "HowItsWorks": "如何運作",
  "LearnMore": "瞭解更多",
  "ContactMenu": "連絡人菜單",
  "HeadquarterHongKong": "FRAYTE物流有限公司香港總部，為您的物流需求提供一切可靠的解決方法",
  "OurAim": "我們的目標是確保貨運和物流活動，以不斷滿足您的需求和期望，同時降低你的操作成本",
  "OpeningTimes": "營業時間",
  "ContactUs": "聯繫我們",
  "Office": "辦公室",
  "Head": "總部",
  "FeelFreeToContact": "今天請隨時聯繫我們，我們的專業小組將為您提供最高水準的服務",
  "SalesInquires": "銷售查詢",
  "sales": "銷售",
  "TheClients": "客戶",
  "TheTeam": "團隊",
  "WideRangeOfCLient": "FRAYTE物流有限公司擁有世界各地廣泛的客戶基礎，他們都期望最好的服務，最短的運輸時間和最低成本。我們為能給他們提供服務感到自豪。以下是一些我們與客戶合作的例子。",
  "Factories": "工廠",
  "Logistic": "物流",
  "Companies": "公司",
  "Brands": "品牌",
  "Retailers": "零售商",
  "DedicatedTeamDescription": "FRAYTE物流有限公司成立了專業團隊，致力於提供全方位的優質客戶服務。擁有多元化的全球團隊，我們能為您提供卓越的國際化物流服務，讓您感覺如像在當地一樣。",
  "HowItsWork": "如何運作",
  "WhatDocumentNeeded": "安排一個裝運需要提供什麼檔",
  "MakeShipment": "安排裝運的時候我們需要您提供以下檔以確保能順利運輸",
  "YouWillBeNeed": "您將需要",
  "AirwayBill": "運單",
  "ToCalculateShipmentWeight": "計算裝運重量",
  "DetermineActualWeight": "確定實際重量",
  "DetermineActualWeightDesc": "實際重量是指實際裝在袋子裡、信封或箱子裡的商品重量，稱重時會四捨五入到最接近的千克數（KG）",
  "CalculateVolumetricWeight": "計算體積重",
  "CalculateVolumetricWeightDesc": "請把裝貨的箱子長度x寬度x高度/5000，我們在出貨的時候會四捨五入到最接近的千克數(KG)",
  "DetermineBillableWeight": "確定計費重量",
  "DetermineBillableWeightDesc": "但確定了這批貨的實際重量和體積重後，我們會比較出最大者，取其作為收費重量。這是用於計算帳單上最終的收費價目。",
  "HowDoCompletePaperWork": "我應怎樣完成文書工作？",
  "HowDoCompletePaperWorkDesc": "我們準備了下面的一些範例，供您參考應如何完成文書工作。 如果你有更多疑問請隨時聯繫我們FRAYTE物流有限公司的代表作更詳盡的瞭解詢問。",
  "Examples": "例子",
  "WhatIsTransitTimeOfGoods": "我的貨物運輸時間是多久？",
  "WhatIsTransitTimeOfGoodsDesc": "請參考我們的價目表和區域運輸時間表",
  "WhatIsMaxWeight": "最大的裝運重量是多大",
  "WhatIsMaxWeightDesc": "最大的裝運重量是多大",
  "Kgs": "千克",
  "PerPiece": "每件",
  "WhatIsMaxLengthOfSinglePackage": "每一個包裝最長的長度是多少？",
  "Cm": "釐米",
  "M": "米",
  "WhatItemNotTransport": "什麼貨物不能運輸",
  "AirFreight": "空運",
  "AirFreightDesc": "航空貨運選項適合移動大量的重型或笨重貨物從A地區到b地區，在進口或出口方面我們的專門小組都樂意提供幫助。",
  "BulkCargoTransportation": "重型貨物運輸",
  "MovingHeavyBulkyShipments": "安排重型貨物運輸",
  "PortToPortDoorToDoor": "港口至港口，門至門服務",
  "PersolnalService": "個人服務",
  "LCL": "散貨拼櫃",
  "FCL": "整櫃貨",
  "SeaFreight": "海運",
  "SeaFreightLCLDesc": "對於裝不滿一整個貨櫃的但仍需走海運的小票貨物，最小要達到2.5CBM，我們能為您安排散貨拼櫃的服務（LCL）。",
  "SeaFreightFCLDesc": "FRAYTE物流有限公司能為您提供完整的裝櫃（FCL）服務，我們會為您提供每週到主要港口的航運時間表。這項服務適合非緊急、體積大、重型、收費裝載量大的貨物運輸。",
  "SmallerShipmentSize": "較小的裝運尺寸",
  "SecureTransportation": "安全運輸",
  "CompetitivePricing": "有競爭力的價格",
  "GlobalNetwork": "全球運輸網路",
  "LargeMovementOfGoods": "大型商品流動",
  "CourierDesc": "我們的快遞運輸網路覆蓋了全球200多個國家，因而能為你提供最快的全球運輸服務，我們還能提供貨物流動資訊，讓您能及時追蹤貨物動態。",
  "GlobalCoverage": "全球覆蓋範圍",
  "DocumentAndNonDocumentShipment": "有文件與無文件裝運",
  "Pre": "預先",
  "dropOff": "交貨",
  "EXPRYESDesc": "如果你需要比快遞服務還要快的服務，我們的直飛服務非常適合您最緊急的運輸需求。擁有最強的靈活性和最快的速度，我們能提供更長的截倉時間，通過我們現存的運輸網路提供門到門的送貨服務。",
  "CoveringMajorCitiesAndBusinessHubs": "覆蓋主要城市與商業中心",
  "PriorityHandling": "優先安排",
  "ExpressClearanceDestinationAirport": "目的港清關服務",
  "LateCutOffTimes": "最遲截倉時間",
  "FlexiblePersonalService": "靈活的個人服務",
  "HandCarryDesc": "我們在全球各地擁有龐大的運輸網路和專業小組，我們能為你提供私人手帶貨物服務，親自交付你的貨物。從開始到最後交貨的全程您都可以即時追蹤到貨運資訊。若您有非常重要的貨物或非常緊急的貨物要交付，我們強烈推薦這個專屬服務。",
  "DedicatedPersonalCourierTravelling": "專用個人快遞服務",
  "RealTimeTracking": "即時追蹤",
  "FastQuotations": "快速報價",
  "QuickestTransitTimes": "快速運輸時間與清關",
  "PickPack": "提貨和包裝服務",
  "BothBondedAndNonBonded": "保稅與非保稅",
  "StockTracking": "庫存跟蹤",
  "InventoryManagement": "存貨管理",
  "WarehousingDistribution": "配送分配",
  "Secure": "安全",
  "BreakBulkServicesAvailable": "卸貨服務",
  "LocalHKTruckingDelivery": "香港本地卡車送貨服務",
  "CopyRight": "版權",
  "FuelSurcharge": "燃油附加費",
  "Forms": "表格",
  "Following": "以下",
  "Transport": "運輸",
  "Stock": "存儲",
  "Draw": "拉",
  "Down": "下",
  "Request": "要求",
  "Packing": "包裝",
  "Template": "模版",
  "Kown": "已知",
  "Consignor": "發貨人",
  "Embroidery": "繡花",
  "Booking": "訂艙",
  "Card": "卡片",
  "AU": "澳洲",
  "N/A": "沒有",
  "Details": "詳情",
  "try": "嘗試",
  "A": "A",
  "Show": "顯示",
  "Hide": "隱藏",
  "Required": "必填",
  "Bulk": "重型",
  "BUTTON_LANG_EN": "English",
  "BUTTON_LANG_CH": "中文",
  "Keys": "關鍵字",
  "Track": "追蹤",
  "Your": "你的",
  "Now": "現在",
  "Print": "列印",

  "United": "United",
  "Kingdom": "Kingdom",




  "Services": "服務項目  ",
  "Air_Freight": "空運   ",
  "Sea_Freight(LCL)": "海運（散貨拼箱）",
  "Sea_Freight(FCL)": "海運（整箱貨）",
  "Service_Key": "服務要點",
  "EXPRYES": "直飛服務",
  "Hand_Carry": "手提急件",
  "PickandPack": "提貨和包裝服務",
  "Warehousing_Distribution": "倉儲與配送",
  "CLIENTS_AND_TEAM": "客戶團隊",
  "FACTORIES": "工廠",
  "LOGISTIC_COMPANIES": "物流公司",
  "BRANDS": "品牌",
  "RETAILERS": "零售商",
  "LEARN_MORE": "了解更多&如何運作",
  "You_Will_Need": "您將需要",
  "HOW_IT_WORKS": "如何運作",
  "Items_Not_Transport": "什麼物品是不能運輸的?",
  "Fuel_Surcharge": "燃油附加費",
  "Last_3_Month": "最近3個月",
  "FRAYTE_FUEL": "FRAYTE燃油",


  "COMMERCIAL_INVOICE_TEMPLATE": "商業發票模板",




  "TRANSPORT_DELIVERY_ORDER": "運輸配送訂單",
  "STOCK_REQUEST": "倉儲需求",
  "PACKING_LIST_TEMPLATE": "裝箱單模板",
  "KNOWN_CONSIGNOR_FORM": " 已知托運人表格",
  "AIRWAY_BILL": "運單",
  "CONTACT_US": " 聯繫我們",
  "Customer_Information": " 客戶信息",
  "Payment_Information": "付款信息",
  "Card_Information": " 信用卡信息",
  "Card_Expiry": "信用卡有效期",
  "Pay_Now": " 現在付款",

  "COLLECTION_ADDRESS": " 收件地址（寄貨人）",
  "DELIVERY_ADDRESS": "送貨地址（收貨人）",


  "Contact_First_Name": " 聯繫人名字",
  "FirstName_Required": " 聯繫人名字",
  "Contact_Last_Name": " 聯繫人姓氏",
  "LastName_Required": " 聯繫人姓氏",

  "Address_1": " 地址1",
  "Address_2": " 地址2",

  "Area": " 地區",

  "Send_Alert_Email": " 手機接收提醒郵件",
  "SHIPMENT_DETAIL": " 運輸詳情",
  "Payment_Party": " 付款方",
  "Payment_required": " 填寫付款方（必須）",
  "Shipment&Package_Info": " 裝運和包裝信息:",
  "Carton_QTY": " 箱數",
  "Length": " 長度",
  "Width": " 寬度",
  "Height": " 高度",
  "Weight": " 重量",
  "Declared_Value": " 申報價值",
  "Shipment_Content": " 運輸內容",
  "Add_More": " 更多",
  "Parcel_Type": "包裹類型",
  "Currency": " 幣種",
  "Shipment_Reference": " 貨件參考",
  "Collection_Date": " 收貨日期",
  "Est_Collection_time": " 預估收貨時間",
  "Clear_Form": "清空表格",
  "Save_Later": " 保存供以後使用",
  "Get_Services": "獲取服務",
  "Place_Booking": " 下訂單",
  "Service_Available": " 可提供的服務",
  "Courier_Name": " 快遞名字",
  "Courier_Description": " 快遞描述",

  "Service_Type": " 業務類型",
  "Total_EstRate": " 預估總體稅率",

  "Note": " 注意",

  "Custom_Declaration": " 海關申報",
  "Shipment_Method": " 運輸方式",
  "Category_Item": " 項目類別",
  "Category_Explanation": " 種類說明",

  "Contents_Error": " 內容有效性說明錯誤",
  "Commodity_Code": " 商品編碼",
  "Commodity_Code_req": " 商品編碼（必須）",
  "Customers": " 客戶",
  "Tracking_No": " 貨物追蹤單號",
  "Frayte_ShipmentNo": " FRAYTE貨物追蹤單號",
  "Logistic_Type": " 物流類型",
  "From_Date": " 從……（日期）",
  "To_Date": " 到……（日期）",
  "Shipment_Status": " 貨件運輸狀態",
  "Search": "搜索",

  "Customer": " 客戶",

  "To_Company": " 收貨公司（收貨人）",
  "Custom_Information": " 自定義信息",
  "Shipment_RefDetail": " 運輸詳細信息參考",

  "Print_Labels": " 打印標籤",
  "Tracking": " 追蹤",
  "Click_Link_Below": " 點擊下面的網頁鏈接",
  "DB_AdvanceFilter": " 直接預約",
  "Download_as_PDF": "以PDF檔形式下載",
  "Placeholder_EmailAddress": "郵箱地址",
  "Send_Label": "發送標籤",
  "Thermo_Label_Print": "列印標籤",
  "A4_Label_Print": "A4標籤列印",
  "Cancel_Shipment": "取消裝運",
  "Close_Window": "關閉窗口",
  "Clone_Shipment": "複製裝運資訊",
  "Payment": "付款",
  "Confirmation": "確認",
  "See_Previous_Address": "請點擊和參看之前的位址",

  "Download_Excel_Tpl": " 下載Excel表格",
  "Upload_Excel_Tpl": " 上傳Excel表格",
  "Frayte_Account": " FRAYTE賬號",
  "Contact_Name": " 聯繫名字",
  "Origin_Country": " 原產國",
  "Origin_Agent": " 原產地代理商",
  "Destination_Country": " 目的國",
  "Destination_Agent": " 目的地代理商",
  "Billing_Address": " 賬單地址",

  "Direct_Booking": " 直接預訂",
  "Tradelane_Booking": "航線預訂",
  "Break_Bulk_Shipment": " 散裝貨物",
  "POD_Email_Settings": " 交貨證明郵件設置",
  "PODMail_Schedule": " 交貨證明郵件日程計畫",
  "Per_shipment": " 每一批貨",
  "Schedule": " 時間表",

  "Daily": " 日",
  "Monthly": " 月",
  "Yearly": " 年",

  "Additional_MailTo": " 附加的郵件發送至……",

  "RateCard_ScheduleDetail": " 價目表詳情",

  "PDF": "PDF",
  "DHL_Express": " DHL快遞",
  "FedEx": " Fedex聯邦快遞",
  "TNT_Express": " TNT快遞",
  "UK/EU_Shipment": " 英國/ 歐洲運輸  ",

  "BusinessUnit_Zone": " 業務範圍區域",
  "Import_MarginCost": " 進口利潤",
  "Export_MarginCost": " 出口利潤",
  "ThirdParty_MarginCost": " 第三方利潤",
  "UKShipment_MarginCost": " 英國運輸利潤)",

  "EUExport_MarginCost": " 歐盟經濟體出口利潤",
  "EUImport_MarginCost": " 歐盟經濟體進口利潤",

  "Zone": " 地區",
  "Margin_Doc": "  有利潤記錄",
  "Margin_Nondoc": " 無利潤記錄",
  "Margin_Doc_Nondoc": " 有利潤記錄&無利潤記錄",
  "Margin_HeavyWeight": " 重量級",
  "Phone_No": " 電話號碼",
  "Manager_Name": " 管理人名字",
  "Manager_Email": " 管理人郵件",
  "First_Name": " 名字",
  "Skype_No": " Skype號碼",
  "Telephone_No": " 電話號碼（必須）",
  "Special_Permission": " 特別許可",
  "FuelSur_Update": " 更新燃油附加稅表",
  "Currency_Update": " 貨幣更新",

  "Operation_Zone": " 運營區域",
  "Zone_Name": "    區域名字",
  "Assign_Countries": "  指定國家",
  "Add_Country": "添加新國家",
  "OperationZone_Name": " 運營區域名字",
  "AddEdit_Zone": " 添加/ 編輯區域 ",
  "Delete_Country": " 刪除國家",
  "UK_Shipment": " 英國運輸",
  "UK_DOMESTIC": "英國運輸",
  "Logistic_Service_Type": " 物流服務類型",
  "Manager_ZoneA": " 區域A管理人",
  "Manager_ZoneB": " 區域B管理人",
  "Manager_ZoneC": " 區域C管理人",
  "Manager_ZoneD": " 區域D管理人",
  "Manager_Zone": " 管理區域",
  "BaseRate_Card": " 基本價目表",
  "Shipment_Type": "運輸類型",
  "Courier_Account": " 快遞帳號",
  "Clear_Filter": " 清除篩選條件",

  "Doc": " 有記錄",
  "Non_doc": " 無記錄",
  "Doc_Nondoc": " 有記錄 &無記錄",
  "Heavy_Weight": " 重量級",

  "Package_Type": "  包裝類型",
  "Parcel_Service_Type": " 包裹業務",
  "Destination_Zone": " 目的地區域",
  "Origin_Zone": " 起點區",
  "AddUpdate_LocationKey": " 添加/ 更新位置密鑰",

  "API_Key": "開發者密鑰",
  "User_Key": " 用戶密鑰",
  "PHK_TrackingShipment": " 追蹤包裹密鑰",
  "Sell": " 賣出",
  "Buy": " 買入",
  "Buy_ExchangeValue": " 買入匯率",
  "Sell_ExchangeValue": " 賣出匯率",

  "AddMore_CurrencyRate": "更多匯率",
  "Ok": " 好",
  "Exchange_Rate": " 匯率",
  "Start_Date": "   開始日期",
  "End_Date": " 結束日期",
  "Year": " 年",


  "Fuel_Surcharge_Percent": " 燃油附加費百分比",
  "Fuel_Month_Year": " 燃油 月 年",
  "Import": " 進口",
  "Export": " 出口",
  "Third_Party": " 第三方",
  "EU_Import": " 歐盟經濟體進口",
  "EU_Export": " 歐盟經濟體出口",

  "Account_ID": " 帳戶ID",
  "Account_No": " 帳戶號碼",

  "AddEdit_ShipmentAccount": " 添加/ 編輯裝運帳戶",
  "EasyPost_CourierId": " 快捷郵政快遞ID",
  "CourierAccount_Number": " 快遞帳戶號碼",
  "Country_Code": "國家編碼",
  "IMP_Import": " 進口",
  "EXP_Export": " 出口",
  "THP_Third_Party": " 第三方",
  "EUI_EU_Import": " 歐盟經濟體進口",
  "EUE_EU_Export": " 歐盟經濟體出口",
  "UKS_UK_Shipment": " 英國運輸",
  "Service_Provider_Id": " 服務提供者ID",
  "Service_Id": " 服務ID",
  "Service_Provider": " 服務提供者",



  "Users": " 用戶",

  "Couriers_Account": " 快遞帳號",
  "Country_Zone": " 國家地區",
  "Zone_Postcode": " 地區郵政編碼",
  "Base_Rate_Card": " 基本價目表",
  "Third_Party_Matrix": " 第三方區域",
  "ParcelHub_Keys": " 包裹中心密鑰",

  "EasyPost_Account": " 快捷郵政快遞帳戶",
  "ParcelHub_Acc": " 包裹中心帳戶",
  "Admin_Frayte": "FRAYTE管理員",






  "Key_Service": "服務要點",
  "Privacy_Policy": "隱私保護",
  "Term_And_Condition": "服務條款",
  "CustomInfo": "客戶信息",

  "Restriction_Explanation": "限制性解釋",


  "Weekly_Day": "一週中的一天",
  "Select_Week_Day": "在一周中選擇一天",
  "Rate_Card_Format": "價目表格式",
  "Customer_RateCard": "客戶價目表",
  "Operation": "運營",
  "POD_Type": "交貨類型",
  "Over_Weight_Charge": "超重收費",
  "Max_Length": "最大長度",
  "Max_Grith": "最安全",
  "Max_Weight": "最大重量",
  "Add_LocationKey": "增加地理位置",
  "Exchange_Value": "汇兑价值",
  "Business_Unit": "營業單位",
  "Generate_Fuel_Surcharge": "產生的燃油附加費",

  "Choose_Colour_Code": "選擇顏色編號",
  "Change_Colour": "更改顏色",
  "ThirdParty_AccountNumber": "第三方帐号",
  "ThirdParty_AccValidation": "第三方帐号（必须）",
  "Total_Shipment_Pieces": "總發貨件數",

  "Currency_required": "貨幣（必須）",
  "Reference_required": "參考文件（必須）",
  "Content_Type": "內容類型",
  "Content_Explanation": "內容解釋",
  "Restriction_Type": "限制性類型",
  "Category_Item_required": "項目種類（必須）",
  "Estimated_Delivery_Date": "預計交貨日期",
  "Estimate_Weight": "預估重量",
  "Signed": "簽名",
  "BY": "由……",
  "Updated": "更新",
  "At": "在",
  "Activity": "活動",
  "Pieces": "件數",




  "PODMail_Detail": "交貨郵件提醒計畫",
  "Time24": "24小時時鐘",
  "RateCard_Schedule": "價目表郵件計畫",
  "QuickDirect_Booking": "快速預訂",
  "ManageDirect_Booking": "追蹤",
  "TopTaxDuties": "付款條款（稅金）",
  "TermsOfPayment": "付款條款（運費）",
  "AccountDepartment": "會計部門名字",
  "Price_Detail": "預計帳單詳情",

  "Lost_data": "這個行為會讓您丟失當前訂艙單的資料",

  "AccountDepartment_Email": "會計部門郵件",
  "Wait_Message": "追蹤細節請等待30分鐘。",
  "contentsType": "內容類別型",
  "contentsTypePlaceHolder": "內容類別型（必填）",
  "contentsTypeValidError": "內容類別型（必填）",

  "contentsExplanation": "內容解釋",
  "contentsExplanationPlaceHolder": "內容解釋（必填）",
  "contentsExplanationValidError": "內容解釋（必填）",

  "restrictionType": "限制類型",
  "restrictionTypePlaceHolder": "限制類型（必填）",
  "restrictionTypeValidError": "限制類型（必填）",


  "restrictionComments": "限制內容",
  "restrictionCommentsPlaceHolder": "限制內容（必填）",
  "restrictionCommentsValidError": "限制內容（必填）",

  "customsCertify": "海關認證",
  "customsCertifyValidError": "海關認證（必填）",

  "customsSigner": "海關簽名",
  "customsSignerPlaceHolder": "海關簽名（必填）",
  "customsSignerValidError": "海關簽名（必填）",

  "nonDeliveryOption": "無法派送選項",
  "nonDeliveryOptionPlaceHolder": "無法派送選項（必填）",
  "nonDeliveryOptionValidError": "無法派送選項（必填）",

  "eelPfc": "EELPFC",
  "eelPfcPlaceHolder": "EELPFC (必填)",
  "eelPfcValidError": "EELPFC（必填）",
  "PaymentParty_TaxandDuties": "付款方稅金 ",
  "TaxandDuties_Message": "誰將支付本次運輸的稅金",

  "Customer_Detail": "客戶詳細資訊",
  "Customer_MarginCost": "客戶邊際成本",



  "Select_CategoryItem": "選擇產品類型",
  "Content_Explanation_Required": "內容解釋（必填）",

  "All": "所有",

  "Option": "選項",
  "Clone": "複製",
  "Create_Return": "創建返回",
  "Track_Shipment": "追蹤運輸",
  "Create_Shipment": "創建裝運",
  "Delete_Draft": "刪除草稿",
  "Estimated_Cost": "預估成本",
  "Estimated_Total_Cost": "預估總成本",

  "History": "歷史",
  "Month": "月",
  "is": "是",
  "Created_On": "創建時間",


  "Choose": "選擇",
  "Choose_Country_Validation": "請選擇一個城市",
  "Amount": "總金額",

  "Total_Paid_Amount": "總計應付金額",
  "No_Validation": "無效數字",
  "Card_No": "信用卡帳號",
  "CardNo_Validation": "信用卡帳號（必填）",
  "ExpMon_Validation": "過期月份（必填）",
  "ExpYear_Validation": "過期年份（必填）",
  "CVC": "CVV",
  "CVC_Validation": "CVV （必填）",

  "Address_Book": "地址簿",
  "New_Address": "添加新地址",
  "Earse_All_Address": "清空所有地址",
  "Address_Type": "網址類別型",
  "TrackingMessage_DetailPage": "請上FRAYTE.co.uk 追蹤物流網頁查詢詳情",
  "Shipment_PkgDetail": "裝運與包裹詳情l",
  "PrintLabel_Message": "如果標籤顯示紅色代表已經被下載了",
  "Carton_Value": "貨箱價值",
  "Reference": "參考",
  "POD_Detail": "交貨提醒詳情",
  "Client_Name": "客戶名字",
  "ScheduleDay_required": "計畫日（必填）",
  "ScheduleDate_Invalid": "計畫日期（必填） ",
  "Total": "總計",
  "Value": "價值",
  "Increased_Overall_Costs": "燃料價格的變化導致了交通行業的總體成本增加,迫使燃油附加費可能上升,下降或移除，這會與燃油價格走勢一致。",
  "Continuingrise_fuelprices": "由於燃料價格持續上漲，FRAYTE物流有限公司認為有需要增加燃油附加費。",
  "OperatingTimes": "營業時間",
  "Time_Validation": "日期必須要後於當前日期",
  "CollectionTime_Required": "收貨時間（必填）",
  "Toaster_ErrorMessage": "錯誤發生，請檢查詳情",
  "Toaster_GetCustomer": "獲取位址簿前請先選擇一個客戶",

  "CMS": "釐米",
  "LB": "磅",
  "INCHS": "英寸",
  "KG": "公斤",
  "Estimated": "估計",
  "Simplified": "簡體",
  "Traditional": "繁體",
  "HH": "小時",
  "MM": "分鐘",
  "RateCard_Note": "注意：如果沒有價格我們會顯示N/A",
  "Allow_Shipper": "允許托運人付稅收和關稅",


  "CreatedAt": "Created At3",
  "TaxAndDuty_Condition": "稅收和關稅情況",
  "ShipperDDPP_Message": "托運人DDP稅收和關稅條件，管理費用可能適用， 請聯繫您的銷售主管",
  "TaxDuty_Accepted": "稅收和關稅被……接受",
  "close": "關閉",
  "DDP_Changes": "確定完稅後交貨",
  "ByDefault_return": "(錯誤)返回",


  "ShipmentCancel_Request": "請求取消裝運",
  "ShipmentCancel_Message": "請求已下達，我們的客服代表會在24小時內聯繫您",
  "ShipmentCancel_Note": "請注意：不是所有運輸都能免費取消的.",
  "SaveDraft_Validation": "至少要填寫裝運國家，目的國家和收貨人，才能保存運輸資料",
  "RateCardSave_Validation": "地區價目表已成功保存",
  "Select_CourierAccount": "請選擇快遞帳號。",
  "THP_Matrix_Saved": "協力廠商資料已成功保存",
  "Record_Saved": "記錄已成功保存",
  "PackageShipment_Validation": "請在這次裝運裡至少添加一個包裹",
  "SelectShipment_Validation": "請在“獲得服務”裡面選擇這次運輸的服務",
  "CustomInformation_Validation": "請選擇合適的海關資訊",
  "BookingSave_Validation": "訂單資訊已成功保存",
  "ServiceSideError_Validation": "Frayte服務終端產生錯誤。請稍後再試",
  "Success": "成功的",
  "RemovePackage_Validation": "不能刪除包裹，請重試",
  "Validation_Error": "合法性錯誤",
  "GetService_Validation": "請填寫所有必須的資料以獲得可用服務",
  "SelectCustomer_Validation": "請先選擇一個客戶",
  "SelectCurrency_Validation": "請先選擇幣種",
  "FrayteWarning_Validation": "FRAYTE警告",
  "SelectCustomerAddressBook_Validation": "請先選擇一個客戶以獲得位址簿",
  "FrayteServiceError_Validation": "FRAYTE服務錯誤",
  "ReceiveDetail_Validation": "無法從伺服器獲取詳情，請稍後再試。",
  "InitialData_Validation": "無法未直接預訂收取初始資料",
  "FrayteError_Validation": "FRAYTE錯誤",
  "GettingDetails_Error.": "獲取詳情時發生錯誤",
  "GeneratePdfError_Validation": "生成pdf檔時發生錯誤",
  "CancelShipmentError_Validation": "取消運輸時發生錯誤",
  "SuccessfullySendlLabel_Validation": "成功向郵箱發送標籤",
  "SendingMailError_Validation": "發送郵件時發生錯誤",
  "EnterValidEmailAdd": "請輸入有效的郵箱位址",
  "TrackShipmentNotTrack_Error": "無法追蹤運輸",
  "ServiceUnavailable_Validation": "無法提供服務",
  "ServiceNotAvailable_Validation": "運輸服務無效，請稍後再試",
  "DeletingShipmentError_Validation": "刪除運輸時發生錯誤",
  "GettingDataError_Validation": "獲取資料時發生錯誤",
  "CustomerDelete_Validation": "已成功刪除客戶",
  "CustomerDeleteError_Validation": "刪除客戶時發生錯誤",
  "UpdateRecord_Validation": "您沒有更新任何記錄 ",
  "RateCardSaveLimit_Validation": "已成功保存地區價目表限制",
  "DataSaved_Validation ": "已成功保存資料",
  "APIkeyUserkey_Saved_Validation": "開發者金鑰和用戶金鑰已成功保存",
  "ParcelHubKeysSavingError_Validation": "保存包裹時發生錯誤",
  "ParcelHubKeyRemoved_Validation": "已成功移除包裹",
  "SelectLogisticType_Validation.": "請至少選擇一種物流類型。",
  "Cancel_Validation": "您確定要取消嗎？",
  "CourierAccountRemoved_Validation": "已成功移除快遞帳號 ",
  "CourierAccountRemovingError_Validation": "移除快遞帳號時發生錯誤，請重試",
  "TrackingDetails_Validation": "請輸入跟蹤詳細資訊",


  "NoServiceAvailable": "無有效服務",
  "CourierCompany": "快遞公司",
  "Assign": "指定",
  "Zone_NotSupported": "該郵遞區號不支援該業務區域",
  "Add/Edit": "添加/編輯",
  "NoAddress_Exist": "不存在的地址",
  "Content_Description": "內容描述",
  "EstimatedWeightNote": "這是預估的重量，不會顯示在實際的收費計重中。",

  "Ratecard_Notvalid": "價目表不適用於這些選項",
  "Ratecard_Getoption": "請選擇適合的選項並搜索以獲得價目表",
  "NoService_Available": "目前無有效服務",
  "TotalEstimate_BillingWeight": "估計的總費用是按實際計費重量計算的",
  "Errors": "錯誤",
  "Section": "部分",
  "Miscelleneous": "其他參數",
  "Issue": "問題",
  "Custom": "自訂",
  "Package": "包裝",
  "AddressRelated_Issue": "出現一些地址相關的問題，請查看詳情。",
  "PackageRelated_Issue": "出現一些包裝相關的問題，請查看詳情。",
  "CustomRelated_Issue": "出現一些關於自訂錯誤的問題，請查看詳情。",
  "CourierRelated_Issue": "出現一些關於快遞服務相關的問題，請查看詳情。",
  "MiscelleneousRelated_Issue": "出現一些關於快遞服務相關的問題，請查看詳情。",
  "CourierAccountNot_Available": "無效的快遞帳號",
  "Currently_Offline": "您現在下線了",
  "Please_Connect": "請連接網路",
  "GrossVolumetric_weight": "總值與容重",
  "AdvanceFilter": "提前搜索篩檢程式",
  "RequestPickup_time": "要求接貨時間",
  "Est_CollectionDate": "預計接貨日期",
  "Matric": "入學許可",
  "Imperial": "紙張尺寸",
  "Supplementary_Charges": "補充費用",
  "To_Consignee": "交收貨人",
  "Total_EstCost": "預估總費用",
  "Uk_Mail": "英國郵政",
  "Yodel": "Yodel",
  "Hermes": "Hermes",
  "Optional_Service": "可選擇受理的業務",
  "Estimated_Chargeable_Weight": "預估總計費重量",
  "FrayteShipment_No": "FRAYTE裝船批號",
  "ToCompany": "公司",
  "System_Alert": "系統警告",
  "Add_Edit": "添加/編輯",
  "Alert_Required": "警告：標題是必填的",
  "Alert_Already_Exist": "警告：標題已經存在",
  "TimeZone_Required": "時區（必填）",
  "TimeZone_Invalid": "無效的時區",
  "AlertDate_Required": "警告：日期是必填的",
  "AlertDate_Alert": "警告：日期無效。",
  "DateShould_Be_Greater": "日期應大於當前日期",
  "Date_Invalid": "無效日期",
  "Date_Required": "日期（必填）",
  "To_": "到",
  "From_": "從",
  "Add_Alert": "添加警告",
  "Download_Template": "下載模版",
  "Upload_File": "上傳文件",
  "QTY": "數量",
  "Select_Option": "下拉選擇功能表",
  "TimeZone_Detail": "時區詳情",
  "Card_Payment_Message": "行政費用適用於信用卡/paypal支付",
  "Declared_Currency": "聲明貨幣",
  "Company_Name": "公司名稱",
  "Supplementary_Charge": "補充費用",
  "Colour_Required": "色號（必填）",
  "Estimated Total Rate": "預估合計比率",
  "From_Shipper": "從發貨人",
  "Deliver": "配送",
  "Enter_Name": "輸入名字",
  "Enter_Email": "輸入郵件",
  "View_BaseRate_Card": "查看基本價目表",
  "Get_Rate": "下載比率",
  "Save_Quote": "保存報價",
  "Copy_From": "從…複製",
  "Allow_Rate_Card": "認可價目表",
  "Registered_Logistic_Services": "已註冊的物流服務",
  "No_Matrix_Available": "沒有矩陣可用於選定的選項.",
  "BaseRateCard_History": "歷史基本價目表",
  "Create_Manifest": "新建艙單",
  "SystemAlert_Heading": "警告服務：標題",
  "SystemAlert_Date": "警告服務：日期",
  "ContactFirstName_Placeholder": "連絡人姓氏（必填）",
  "ContactLastName_Placeholder": "連絡人名字（必填）",
  "Manifest": "艙單",
  "Short_Name": "簡稱",
  "ShortNameValidationError": "簡稱（必填）",
  "Is": "是",
  "Colour": "色號",
  "Over": "超過",
  "WillBe_BilledAt": "將會收取…費用",
  "AddEdit_BaseRateCard_Without_A/C": "無帳號添加/編輯價目表",
  "AddEdit_Currency_Courier_A/C": "添加/編輯幣種和快遞帳號",
  "Dedicated_Service_Team": "你希望從我們專門的客戶服務團隊專門派人跟進嗎？ ",
  "By_filling_validation": "請確認你填寫的海關簽名和報關的資訊是真實和正確的。FRATYE物流有限公司不負責由此造成的任何問題或因此造成的延遲裝運。",
  "Customer_Margin": "利潤計算器",
  "Confirmation_message": "請確認你是否想離開本頁面？",
  "Frayte_Fuel_Percent": "FRAYTE燃油附加費比率",
  "Exprye_Fuel_Percent": "Expryes 燃油附加費比率",
  "Margin_Rate": "盈利率",
  "Service_Option": "服務選項",
  "TelephoneNo": "電話號碼.",
  "Zone_Setting": "區域設置",
  "Tracking_Code": "追蹤號碼",
  "Download_The_Following_Forms": "下載表格",
  "BOOKING_FORM_SEA": "海運服務訂艙單 ",
  "BOOKING_FORM_EXPRYES": "EXPRYES 服務訂艙單",
  "BOOKING_FORM_COURIER": "快遞服務訂艙單",
  "BOOKING_FORM_AIR": "空運服務訂艙單",
  "AccountName_Required": "帳戶名稱（必填）",
  "Mark_Default_WorkingkDays": "標記為預設工作日",
  "Exchange_Rate_Required": "匯率（必填）.",
  "Consignment_Tracking": "追蹤托運貨物",
  "Incorrect_Tracking_Number": "不正確的查詢號碼",
  "NotValid_TrackingCode": "您輸入的是無效的查詢號碼。查詢號碼應該像這樣的：PM_123456_654321",
  "Find_Order_Detail": "您可以在您的帳戶裡找到訂單細節。",
  "Click_Valid_Tracking_Code": "點擊這裡並輸入有效的查詢號碼.",
  "Please": "請",
  "DownLoad_Quote": "下載報價表",
  "Logistics_Company": "無聊公司 ",
  "Set_Margin_Percentage": "設置利潤比率",
  "Margin_Option": "盈利率",
  "MarginCostare_not_available": "無效的邊際成本",
  "FRAYTE_Booking_Confirmation": "感謝使用Frayte物流有限公司。Thank you for using FRAYTE Ltd. 我們的系統正在處理你的裝運資訊，這個過程可能需要60秒，請耐心等待。一旦完成你的訂單資訊將會自動確認。",
  "Please_Wait": "請稍候",
  "FRAYTE_Customer_Service_Team": "FRAYTE 客戶服務團隊",
  "Kindly_Regards": "此致敬意",
  "ImpGuide": "進口指南",
  "Actions": "活動",
  "Action": "活動",
  "Rate_Type": "比率類型",
  "Heading": "標題",
  "View": "流覽",
  "Search_The_Address": "搜索地址",
  "Erase_AllAddress": "你確定要清除所有位址嗎？",
  "Delete_Confirmation": "刪除確認",
  "Delete_Address": "你確定要刪除所有位址嗎",
  "Delete_Courier_Account": "你確定要刪除快遞帳號嗎？ ",
  "Successfull": "成功",
  "Courier_Account_Deleted_Successfully": "成功刪除快遞帳號。",
  "AddressBook_Erased_Successfully": "成功清除地址簿。",
  "Error_While_Deleting_The_Records": "刪除記錄時發生錯誤。",
  "Address_Deleted_Successfully": "成功刪除地址。",
  "System_Alert_Confirmation": "系統警告資訊",
  "Delete_The_Alert": "你確定要刪除這個警告嗎？",
  "Record_Deleted_Successfully": "成功刪除記錄",
  "Frayte_Success": "FRAYTE 成功",
  "Frayte_Error": "FRATYE 錯誤",
  "Error_While_Getting_Record": "獲得記錄時發生錯誤",
  "Manifest_Name": "艙單名稱",
  "Downloaded_Status": "下載狀態",
  "Report_Generated_Successfully": "報告已成功生成並從系統下載成功。請查看你的流覽器下載檔案夾。",
  "Report_Status": "報告狀態",
  "Could_Not_Download_TheReport": "不能下載報告，請重試",
  "No_Report_Generated": "沒有生成報告，請重試",
  "SelectAtleast_OneManifest": "請至少選擇一張艙單",
  "ErrorWhileCreating_Manifest": "創建艙單時發生錯誤",
  "Error": "錯誤",
  "SUCCESS": "成功",
  "Manifest_Created_Successfully": "成功創建艙單",
  "Select_Parcel_Type": "選擇包裹類型",






  "Please_GOTO": "Please go to3",
  "Shipment_Types": "Shipment Types3",
  "Frayte_co_uk": "Frayte.co.uk3",
  "Frayte_com": "Frayte.com3",
  "TrackingPageToTtrackthe_Detail": "tracking page to track the detail3",
  "Get_Quotation": "Get Quotation3",
  "LetterParcelCan_NotGreaterThanTwo": "Letter parcel can not be greater then 2 kg3",
  "My_Rate": "My Rate3",
  "PleaseWaitWhile_ProcessingService": "Please wait while processing service3",
  "PleaseWaitWhile_Placing_Booking": "Please wait while placing booking3",
  "TakeUpTo_60Seconds": "take up to 60 seconds3",
  "ThankYouFor_UsingFRAYTELogisticsLtd": "Thank you for using FRAYTE Logistics Ltd. We are now processing your Shipment in our system, which can3",
  "Please_RemainOn_This_Screen": "Please remain on this screen. You will be directed automatically to our Booking Confirmation screen upon completion.3",
  "Quote_": "Quote3",
  "PleaseWaitWhile_Get_Rate": "Please wait while we prepare your quote...3",
  "ThankYouFor_UsingFRAYTELogisticsLtdRate": "Thank you for using FRAYTE Logistics Ltd. We are now processing your request for a quote in our system, which can3",
  "Please_RemainOn_This_ScreenRate": "Please remain on this screen. You will be directed automatically to our quotation confirmation screen upon completion.3",
  "Postcode": "Postcode3",
  "ToTime_Required": "To Time is required3",
  "AllQuote_Issue_FRAYTE": "All quotes issued are subject to FRAYTE Logistics Ltd final acceptance and full Terms & Conditions.3",
  "Email_Quote": "Email Quote3",
  "Confirm_Quote": "Confirm Quote3",
  "Validate_For_Pay": "Validate For Pay3",
  "CardExpiryis_required": "Card Expiry is required3",
  "3Digit_Card_Verification_Number": "3-digit card verification number3",
  "Credit_Card": "Credit Card3",
  "Quotation_Tool": "Quotation Tool3",
  "Courier_Company": "Courier Company3",
  "DownLoad_Excel": "Download Excel3",
  "Service_Alert": "Service Alert3",
  "Estimated_Total_Rate": "Estimated Total Rate3",
  "Estimated_Rate": "Estimated Rate3",
  "My_Quotes": "My Quotes3",
  "IDECLAREMYSHIPMENT_CONTAINSNON_HAZARDOUS_CONTENT": "I DECLARE MY SHIPMENT CONTAINS NON HAZARDOUS CONTENT !3",
  "Summary": "Summary3",
  "Direct_Booking_Hover": "Direct Booking system is a courier booking platform, allowing you to compare and generate shipping labels for many of the leading couriers, both internationally and domestically. Our online system will allow you to choose the right courier for the job.3",
  "Direct_Booking_Warehousing": "Warehousing (WMS) system allows you to keep up to date with your stock that is in store in one of our global warehouses. Pick requests can either be uploaded or entered manually, giving you total control of your inventory on a global basis with a click of a button. Alongside of this our dedicated team of drivers and vehicles provide the very best in terms of distribution.3",
  "Direct_Booking_Breakbulk": "Breakbulk allows you to have multiple consignments consolidated and labeled at origin. Air or Sea freighted from origin to destination before being Customs cleared by one Importer on Record before being injected into a local domestic delivery network. Giving you a door to door fulfillment solution on a global basis.3",
  "Direct_Booking_Ecommerce": "eCommerce product allows you to choose from our wide range of distribution services for your online business fulfillment needs. Specialists in handling large numbers of small packets from both branded courier solutions to unbranded solutions, giving you a product that is quicker than the postal networks but slower, and lower in cost, than the express courier.3",
  "Direct_Booking_Tradelane": "Tradelane booking service is set up for Air and Sea Freight (LCL and FCL) for regular shipment bookings from multiple sources at origin to delivery to your warehouse / office at destination. The systematic approach of the software allows you consistent handling for all shipments.3",
  "Direct_Booking_Express_Air": "Looking for some thing in a hurry. Express Solutions have three unique products from booking a Next Flight Out (NFO), On Board Courier hand carry service across the globe, to arranging a true next day Express Courier service all over the world. We have the solutions for your EXPRESS Shipments.3",
  "Decl_Est_Weight": "Declared Estimated Weight3",
  "TotalEstimate_BillingWeightGetServices": "Total estimated charges may vary depending on actual billable weight, All Services are subject to FRAYTE Logistic Ltd. final acceptance and full Terms and Conditions.3",
  "Email_NotificationConsignee": "Send Email Delivery Notification.3",
  "Email_NotificationShipper": "Send Email Delivery Notification.3",
  "Payment_Details": "Payment Details3",
  "FRAYTE_Invoice_Number": "FRAYTE Invoice Number3",
  "Quotation_": "Quotation3",
  "Manifests": "Manifests3",
  "Days_Validity": "Days Validity3",
  "csv": "csv3",
  "xlsx": "xlsx3",
  "xls": "xls3",
  "Please_Contact": "Please contact3",
  "FAQ_s": "FAQ's3",
  "Tracking_Frayte_Dot_Com": "tracking@frayte.com3",
  "Select_PostCodeAddress": "Select Postcode Address3",
  "PostCode_Address": "Postcode Address3",
  "Select_Shipment_Type": "Select Shipment Type3",
  "ACustomer_Record": "a customer record ?3",
  "Square": "List View3",
  "Square_Format": "click here to view address in list format3",
  "Grid": "Grid View3",
  "Grid_Format": "click here to view address in grid format3",
  "Agree_Term_And_Condition": "agree to our Terms and Conditions",
  "ToCc_": "To CC3",
  "ToBCc_": "To BCC3",
  "ToCc_Email": "To CC Email3",
  "ToBCc_Email": "To BCC Email3",
  "Breakbulk": "Break Bulk3",
  "Ecommerce": "eCommerce3",
  "Express": "Express3",
  "Solutions": "Solutions3",
  "Warehouse_Transport": "Warehouse3",
  "And": "&3",
  "Dear": "Dear3",
  "Notes_Condition": "Notes/Conditions:3",
  "Special_Offer_Valid": "1. The above special offer is valid for an ad hoc shipment and is subject to final acceptance of full Terms and Conditions.3",
  "Payment_Within_Agree_Terms": "2. Payment within the agreed terms.3",
  "Not_Responing_Taxes_Duties": "3. FRAYTE Logistics Ltd. is not responsible for any duties or taxes imposed by the destinations country.3",
  "Shipment_Charges_Volumetric_Weight": "4. Shipment Charges are based on volumetric weight (Length cm x Width cm x Depth cm / 5000); 200 kg / 1CBM or gross weight, whichever is the greater.3",
  "Only_General_Cargo_Quote": "5. Quote is for General cargo only.3",
  "FRAYTE_Logistics_Ltd": "FRAYTE Logistics Ltd.3",
  "kGS": "kGS3",
  "Generator": "Generator3",
  "Warehouse_Supprt": "Warehouse & Transport3",
  "Sales_": "sales@3",
  "Alert_Heading": "Alert Heading3",
  "Shipment_Description": "Shipment Description3",
  "Darft_Delete": "Successfully deleted draft shipment.3",
  "LBs": "lbs3",
  "TwentyFour_Hours": "24 hours3",
  "Refund_Policy": "Refund Policy3",
  "Payment_Security": "Payment Security3",
  "Payment_Methods": "Payment Methods3",
  "Termsof_Use": "Terms of Use3",
  "Email_Us": "Email Us3",
  "Call_Us": "Call Us3",
  "Chat_Us": "Live Chat3",
  "General": "General3",
  "Home": "Home3",
  "About_us": "About us3",
  "About_FRAYTE": "About FRAYTE3",
  "Sales_frayte_Dot_Com": "sales@frayte.com3",
  "Call": "Call3",
  "Send_Consignment": "Send a consignment3",
  "Packaging": "Packaging3",
  "Paperwork": "Paperwork3",
  "Commercial_Invoice_Guide": "Commercial Invoice Guide3",
  "Transit_Times": "Transit Times3",
  "Restricted_Items": "Restricted Items3",
  "Restricted_ItemsAndProhibited_Items": "Restricted & Prohibited Items3",
  "Shipping_Lithium_Batteries": "Shipping Lithium Batteries3",
  "Volumetric_Calculator": "Volumetric Calculator3",
  "Using_FRAYTE": "Using FRAYTE3",
  "Booking_Consignment": "Booking a consignment3",
  "Online_Booking_Guide": "Online Booking Guide3",
  "Tracking_Your_Consignment": "Tracking your consignment3",
  "FRAYTE_Forwarding": "FRAYTE Forwarding3",
  "E_Commerce": "eCommerce3",
  "eCommerce_Paragraph": "eCommerce product allows you to choose from our wide range of distribution services for your online business fulfillment needs. Specialists in handling large numbers of small packets from both branded courier solutions to unbranded solutions, giving you a product that is quicker than the postal networks but slower, and lower in cost, than the express courier.3",
  "FRAYTE_Forwarding_Paragraph": "Trade lane booking service is set up for Air and Sea Freight (LCL and FCL) for regular shipment bookings from multiple sources at origin to delivery to your warehouse / office at destination. The systematic approach of the software allows you consistent handling for all shipments.3",
  "Courier_Paragraph": "Direct Booking system is a courier booking platform, allowing you to compare and generate shipping labels for many of the leading couriers, both internationally and domestically. Our online system will allow you to choose the right courier for the job.3",
  "Download_Commercial_Invoice": "Download Commercial Invoice3",
  "Sales_frayte_Dot_Uk": "sales@frayte.co.uk3",
  "Manifest_Number": "Manifest Number3",

  "Road_Surcharge_Percent": " Road Fuel Surcharge Percentage3",
  "Date_Time": "(Date & Time)3",
  "Road_Fuel": "Road Fuel3",
  "Download_Forms": "Download Forms3",
  "ByDefault_None": "(By Default None)3",
  "ByDefault_N/A": "(By Default N/A)3",
  "CourierTracking_No#": "Courier Tracking No.#3",
  "ShipmentDetail": "Shipment Detail3",
  "CountrtyZone_Postcode": "Country Zone Post/Zip Code3",
  "AssignPostcode_Warning": "You cannot assign post/zip code to this country and zone3",
  "Access_Level": "Access Level3",
  "Secure_Payment_Gateway": "Secure Payment Gateway3",
  "Advance_Rate_Card": "Advance Rate Card3",
  "Normal_Margin_Rate": "Normal Margin Rate3",
  "Advance_Margin_Rate": "Advance Margin Rate3",
  "UserDetail": "User Detail3",
  "AdvanceRatecard_Getoption": "Select proper options and click search to get advance rate card3",
  "AdvanceRatecard_Notvalid": "Advance rate card is not available for these selected options3",
  "SetRate_CArd": "First need to save rate card3",
  "HsCode_Jobs": "Jobs3",
  "NO_HSCode_Jobs": "Total Jobs with no HS codes3",
  "HSCode_Operators": "Total Operators3",
  "Jobs_Per_Hour": "Total HS codes output / operator / hour3",
  "Jobs_In_Progress": "Total Jobs in progress3",
  "Operators_Details": "Operators Details3",
  "Jobs_Operator_Hour": "Jobs Operator Hour3",
  "Operators": "Operators3",
  "Operator": "Operator3",
  "Avg_Jobs_Completed_Per_Hour": "Avg. jobs completed per Hour3",
  "Jobs_Assigned": "Jobs Assigned3",
  "Show_Jobs_Per_Page": "Show jobs per page3",
  "All_Select": "Select All3",
  "HS_Code_Lookup": "HS Code Lookup3",
  "Show_Jobs_In_Progress_Per_Page": "Show jobs in progress per page3",
  "FRAYTE_Ref#": "FRAYTE Ref#3",
  "Staff_Assigned": "Staff Assigned3",
  "Origin": "Origin3",
  "Description_Of_Goods": "Description of Goods3",
  "Completed_Job_OR_Total_No_Of_Jobs": "Completed jobs / Total no. of jobs3",
  "HS_Codes": "HS Codes3",
  "Removed_shipment": "Successfully removed the shipment from manifest3",
  "Removed_shipment_error": "An error occur while removing shipment from manifest. Please try again later.3",
  "Error_registering_service": "Error While registering service3",
  "RateCard_Generated_Successfully": "Base rate card excel downloaded successfully in your system. Please check browser download folder.3",
  "Could_Not_Download_RateCard": "Could not download the base rate card excel. Please try again.3",
  "Error_downloading_baserateexcel.": "Error while downloading base rate card excel.3",
  "Could_Not_SelectService": "Could not select service due to some problem. Please try again.3",
  "Report_GeneratedDownloaded_Successfully": "Report generated and downloaded successfully in your system. Please check browser download folder.3",
  "Nosupplymentry_charges_Courier": "No supplymentry charges for this Courier.3",
  "Error_DownloadingPDF": "Error in Downloading PDF3",
  "SuccessfullySentMail": "Successfully sent an email3",
  "Select_ServiceFirst": "Select Service First3",
  "Quotationcannotplaced_offervalidityexpired.": "This quotation cannot be placed because offer validity days has expired.3",
  "Error_while_downloading": "Error while downloading. Please try again.3",
  "PleaseCorrectValidationErrors_GetServices": "Please correct the validation errors to get services.3",
  "Please_SelectService": "Please select service first.3",
  "RateCard_GeneratedDownloaded_Successfully": "RateCard downloaded successfully in your system. Please check browser download folder.3",
  "Error_DownloadingExcel": "Error in Downloading Excel3",
  "MarginRate_Save": "Margin rates saved successfully3",
  "Services_alertadded": "Services alert information added successfully.3",
  "Services_alertupdated": "Services alert information updated successfully.3",
  "Errorwhilesaving_Alert": "Error while saving Alert. Try again after some time.3",
  "Terms_And_Conditions": "Terms and Conditions3",
  "Delivery_Address": "Delivery Address3",
  "Collection_Address": "Collection Address3",
  "Cartons": "Cartons3",
  "NoResult_Postcode": "No result for this Postcode3",
  "Remaining_Characters": "Shipment Reference is required and can have3",
  "Char_Added": "character entered3",
  "Character_": "Character3",
  "Search_Users": "Search Users3",
  "FRAYTE_System_Role": "FRAYTE System Role3",
  "ProofOfDelivery_Detail": "Once our team has delivered your consignment, either locally or on the other side of the globe, we will email you with proof of delivery (Daily, Weekly, and Monthly). The timing of this notification is dependent on which service you have chosen.3",
  "ProofOfDelivery_Last_Line": "Should you need any further assistance we would ask that you contact3",
  "Tracking_MailCOUK": "tracking@frayte.co.uk3",
  "Transit_Time": "Transit Time3",
  "BookingConsignment": "Booking Consignment3",
  "FRAYTE_Logistics_Ltd_will_provide_you_with_the_login": "FRAYTE Logistics Ltd. will provide you with the login to our direct booking system allowing you to place the booking online. Upon placing the booking you will be able to create, download and print the labels that are needed for the shipment.3",
  "If_you_book_your_consignments_online": "If you book your consignments online then our online system can automatically store the consignee’s address and also produce the following documentation:3",
  "Consignment_Number": "Consignment Number3",
  "Courier_Labels": "Courier Labels3",
  "Drivers_Collection_Manifest": "Driver’s Collection Manifest.3",
  "In_Order_To_Save_Any_Unnecessary": "In order to save any unnecessary holdups with your delivery once it reaches its destination, if the consignment is dutiable and is consigned to a country outside of the EU (i.e Non EU Country), the courier would need a Commercial Invoice before they are able to pick up the consignment. Should you need any assistance with this please feel free to contact us3",
  "Transit_Times_Vary_From_Courier": "Transit times vary from courier to courier. In order to get the most up to date transit time information we would request you get in contact with one of our team3",
  "Howeverit_Shouldbe_Noted": "However it should be noted, while we always quote estimated transit times nothing is guaranteed and delays can occur due to Customs and flight delays which are outside FRAYTE Logistics Ltd.’s control.3",
  "The Advantage_You_Will_Have_Is": "The advantage you will have is, unlike many other courier companies, we are able to keep you up to date with your shipment every step of the way in the form of consolidated tracking information, even if you are using multiple courier companies both domestically and internationally.3",
  "FRAYTE_Dot_Com": "www.frayte.com3",
  "FRAYTE_CO_Dot_UK": "www.frayte.co.uk3",
  "If_You_Need_Any_Further_Help_OR_Customization": "If you need any further help or customization for this then please feel free to call a member of our team to help.3",
  "FRAYTE_Logistics_Ltd_Is_Able_To_Provide_State": "FRAYTE Logistics Ltd is able to provide state of the art tracking services. This will ensure that you are always able to find and track your shipment when it is moving around the globe. We have our online tracking website at3",
  "Dimensions": "Dimensions3",
  "Delivery_Deadline": "Delivery Deadline.3",
  "Commodity": "Commodity3",
  "Collection_Time": "Collection Time3",
  "Service_Required": "Service Required3",
  "Purchase_Order": "Purchase Order3",
  "Account_Contact": "Account Contact3",
  "Delivery_Town_And_Country": "Delivery Town & Country3",
  "EDI": "EDI3",
  "White_Label_Sites": "White Label Sites3",
  "API_Links": "API Links3",
  "Integration": "Integration.3",
  "If_You_Need_Further_Help": "If you need further help we are always around and happy to help at FRAYTE Logistics Ltd. Feel free to drop us an email3",
  "Our_Team_Will_Be_More_Than_Happy_To_Help_You": "or give us a call and one of our team will be more than happy to help you and guide you through the process. Make sure before you call you have the following information ready:3",
  "We_Also_Have_Options_Of": "We also have options of:3",
  "Booking_In_A_Consignment_Couldnot_Be_Easier": "Booking in a consignment couldn’t be easier when working with FRAYTE Logistics Ltd. Our direct booking is quick and simple to use.3",
  "Option_":  "Option3"
}
